<?xml version="1.0"?>
<odoo>
    <data>

        <!-- template form -->
        <record id="view_fleet_vehicle_filtre_template_form" model="ir.ui.view">
            <field name="name">fleet.vehicle.filtre.template.form</field>
            <field name="model">fleet.vehicle.filtre.template</field>
            <field name="arch" type="xml">
                <form string="Template filtre">
                  <sheet>
                       <group>
                         <field name="name" />
                         <field name="model_id"/>
                         <field name="meter" />
                       </group>
                       <notebook>
                          <page string="Remplacement">
                              <field name="line_ids"  >
                                   <tree string="Remplacement" editable="bottom">
                                       <field name="product_id" context="{'default_spare_ok':1}"/>
                                       <field name="product_qty" />
                                   </tree>
                              </field>
                          </page>
<!--                           <page string="Vérifications">
                              <group col="2">
                                <group>
                                 <field name="checklist_ids1">
                                     <tree string="Niveau" editable="bottom">
                                         <field name="name" domain="[('code','=','niveau')]" context="{'default_code': 'niveau'}"/>
                                     </tree>
                                 </field>
                                </group>
                                <group>
                                 <field name="checklist_ids2">
                                     <tree string="Graissage" editable="bottom">
                                         <field name="name" domain="[('code','=','graissage')]" context="{'default_code': 'graissage'}"/>
                                     </tree>
                                 </field>
                                </group>
                                <group>
                                 <field name="checklist_ids3">
                                     <tree string="Pression" editable="bottom">
                                         <field name="name" domain="[('code','=','pression')]"  context="{'default_code': 'pression'}"/>
                                     </tree>
                                 </field>
                                </group>
                                <group>
                                 <field name="checklist_ids4">
                                     <tree string="Remplacement huile" editable="bottom">
                                         <field name="name" domain="[('code','=','huile')]" context="{'default_code': 'huile'}"/>
                                     </tree>
                                 </field>
                                </group>
                                <group>
                                 <field name="checklist_ids5">
                                     <tree string="Autres entretiens" editable="bottom">
                                         <field name="name" domain="[('code','=','autres')]" context="{'default_code': 'autres'}"/>
                                     </tree>
                                 </field>
                                </group>
                               </group>
                              </page> -->
                         </notebook>        
                   </sheet>
                </form>
            </field>
        </record>

        <record id="view_fleet_vehicle_filtre_template_tree" model="ir.ui.view">
            <field name="name">fleet.vehicle.filtre.template.tree</field>
            <field name="model">fleet.vehicle.filtre.template</field>
            <field name="arch" type="xml">
                <tree string="FILTRES">
                         <field name="name" />
                         <field name="meter" />
                         <field name="model_id" />
                </tree>
            </field>
        </record>

         <!-- action filtre template -->
        <record id="action_fleet_vehicle_filtre_template" model="ir.actions.act_window">
            <field name="name">Template Tableau d'Entretiens</field>
            <field name="type">ir.actions.act_window</field>
            <field name="res_model">fleet.vehicle.filtre.template</field>
            <field name="view_type">form</field>
            <field name="view_mode">tree,form</field>
        </record> 


        <record id="view_fleet_vehicle_filtre_template_filter" model="ir.ui.view">
            <field name="name">fleet.vehicle.filtre.template.search</field>
            <field name="model">fleet.vehicle.filtre.template</field>
            <field name="arch" type="xml">
                <search string="Tableau d'entretien template">
                    <field name="model_id"/>
                    <group expand="0" string="Group By">
                    	<filter name="group_by_model_id" string="Modèle" context="{'group_by':'model_id'}"/>
                        <filter string="Revision" name="group_by_name" context="{'group_by':'name'}"/>
                    </group>
               </search>
            </field>
        </record> 

        <!-- template form -->
        <record id="view_fleet_vehicle_filtre_form" model="ir.ui.view">
            <field name="name">fleet.vehicle.filtre.form</field>
            <field name="model">fleet.vehicle.filtre</field>
            <field name="arch" type="xml">
                <form string="Template filtre">
                  <sheet>
                       <group>
                         <field name="name" />
                         <field name="vehicle_id"/>
                         <field name="meter" />
                       </group>
                       <notebook>
                          <page string="Remplacement">
                              <field name="line_ids"  >
                                   <tree string="Remplacement" editable="bottom">
                                       <field name="product_id" context="{'default_spare_ok':1}"/>
                                       <field name="product_qty" />
                                   </tree>
                              </field>
                          </page>
<!--                           <page string="Vérifications">
                              <group col="2">
                                <group>
                                 <field name="checklist_ids1">
                                     <tree string="Niveau" editable="bottom">
                                         <field name="name" domain="[('code','=','niveau')]" context="{'default_code': 'niveau'}"/>
                                     </tree>
                                 </field>
                                </group>
                                <group>
                                 <field name="checklist_ids2">
                                     <tree string="Graissage" editable="bottom">
                                         <field name="name" domain="[('code','=','graissage')]" context="{'default_code': 'graissage'}"/>
                                     </tree>
                                 </field>
                                </group>
                                <group>
                                 <field name="checklist_ids3">
                                     <tree string="Pression" editable="bottom">
                                         <field name="name" domain="[('code','=','pression')]"  context="{'default_code': 'pression'}"/>
                                     </tree>
                                 </field>
                                </group>
                                <group>
                                 <field name="checklist_ids4">
                                     <tree string="Remplacement huile" editable="bottom">
                                         <field name="name" domain="[('code','=','huile')]" context="{'default_code': 'huile'}"/>
                                     </tree>
                                 </field>
                                </group>
                                <group>
                                 <field name="checklist_ids5">
                                     <tree string="Autres entretiens" editable="bottom">
                                         <field name="name" domain="[('code','=','autres')]" context="{'default_code': 'autres'}"/>
                                     </tree>
                                 </field>
                                </group>
                               </group>
                              </page> -->
                         </notebook>        
                   </sheet>
                </form>
            </field>
        </record>

        <record id="view_fleet_vehicle_filtre_tree" model="ir.ui.view">
            <field name="name">fleet.vehicle.filtre.tree</field>
            <field name="model">fleet.vehicle.filtre</field>
            <field name="arch" type="xml">
                <tree string="FILTRES">
                         <field name="name" />
                         <field name="meter" />
                         <field name="vehicle_id" />
                         <field name="model_id" />
                </tree>
            </field>
        </record>

         <!-- action filtre template -->
        <record id="fleet.action_fleet_vehicle_filtre" model="ir.actions.act_window">
            <field name="name">Modèle d’entretien</field>
            <field name="type">ir.actions.act_window</field>
            <field name="res_model">fleet.vehicle.filtre</field>
            <field name="view_type">form</field>
            <field name="view_mode">tree,form</field>
        </record> 

        <record id="view_fleet_vehicle_filtre_filter" model="ir.ui.view">
            <field name="name">fleet.vehicle.filtre.search</field>
            <field name="model">fleet.vehicle.filtre</field>
            <field name="arch" type="xml">
                <search string="Tableau d'entretiens">
                    <field name="vehicle_id"/>
                    <group expand="0" string="Group By">
                    	<filter name="group_by_vehicle_id" string="Modèle" context="{'group_by':'vehicle_id'}"/>
                        <filter string="Revision" name="group_by_name" context="{'group_by':'name'}"/>
                    </group>
               </search>
            </field>
        </record> 
      </data>
</odoo>   